fds/__init__.py
fds/sdk/__init__.py
fds/sdk/BondsAPIforDigitalPortals/__init__.py
fds/sdk/BondsAPIforDigitalPortals/api_client.py
fds/sdk/BondsAPIforDigitalPortals/configuration.py
fds/sdk/BondsAPIforDigitalPortals/exceptions.py
fds/sdk/BondsAPIforDigitalPortals/model_utils.py
fds/sdk/BondsAPIforDigitalPortals/rest.py
fds/sdk/BondsAPIforDigitalPortals/api/__init__.py
fds/sdk/BondsAPIforDigitalPortals/api/debt_instrument_api.py
fds/sdk/BondsAPIforDigitalPortals/apis/__init__.py
fds/sdk/BondsAPIforDigitalPortals/model/__init__.py
fds/sdk/BondsAPIforDigitalPortals/model/attributes_member.py
fds/sdk/BondsAPIforDigitalPortals/model/cursor_based_pagination_output_object.py
fds/sdk/BondsAPIforDigitalPortals/model/cursor_based_pagination_output_object_without_total.py
fds/sdk/BondsAPIforDigitalPortals/model/debt_instrument_issuer_search_data.py
fds/sdk/BondsAPIforDigitalPortals/model/debt_instrument_issuer_search_data_country.py
fds/sdk/BondsAPIforDigitalPortals/model/debt_instrument_issuer_search_data_market.py
fds/sdk/BondsAPIforDigitalPortals/model/debt_instrument_issuer_search_data_minimum_rating_grade.py
fds/sdk/BondsAPIforDigitalPortals/model/debt_instrument_issuer_search_data_minimum_rating_grade_debt_instrument.py
fds/sdk/BondsAPIforDigitalPortals/model/debt_instrument_issuer_search_data_name.py
fds/sdk/BondsAPIforDigitalPortals/model/debt_instrument_issuer_search_meta.py
fds/sdk/BondsAPIforDigitalPortals/model/debt_instrument_notation_screener_search_data.py
fds/sdk/BondsAPIforDigitalPortals/model/debt_instrument_notation_screener_search_data_compliance.py
fds/sdk/BondsAPIforDigitalPortals/model/debt_instrument_notation_screener_search_data_compliance_germany.py
fds/sdk/BondsAPIforDigitalPortals/model/debt_instrument_notation_screener_search_data_coupon.py
fds/sdk/BondsAPIforDigitalPortals/model/debt_instrument_notation_screener_search_data_coupon_current_interest_rate.py
fds.sdk.BondsAPIforDigitalPortals-0.10.2.dist-info/LICENSE
fds.sdk.BondsAPIforDigitalPortals-0.10.2.dist-info/METADATA
fds.sdk.BondsAPIforDigitalPortals-0.10.2.dist-info/WHEEL
fds.sdk.BondsAPIforDigitalPortals-0.10.2.dist-info/top_level.txt
fds.sdk.BondsAPIforDigitalPortals-0.10.2.dist-info/RECORD
